{
  "predictions": [],
  "data": {
    "ID": 712,
    "p_data": {
      "Pclass": 1,
      "Name": "Klaber, Mr. Herman",
      "Sex": "male",
      "Age": -1.0,
      "SibSp": 0,
      "Parch": 0,
      "Ticket": "113028",
      "Fare": 26.55,
      "Cabin": "C124",
      "Embarked": "S"
    }
  },
  "annotations": [
    {
      "result": [
        {
          "from_name": "sentiment_class",
          "to_name": "message",
          "type": "choices",
          "readonly": false,
          "hidden": false,
          "value": {
            "choices": "Died"
          }
        }
      ]
    }
  ]
}