{
  "predictions": [],
  "data": {
    "ID": 439,
    "p_data": {
      "Pclass": 1,
      "Name": "Fortune, Mr. Mark",
      "Sex": "male",
      "Age": 64.0,
      "SibSp": 1,
      "Parch": 4,
      "Ticket": "19950",
      "Fare": 263.0,
      "Cabin": "C23 C25 C27",
      "Embarked": "S"
    }
  },
  "annotations": [
    {
      "result": [
        {
          "from_name": "sentiment_class",
          "to_name": "message",
          "type": "choices",
          "readonly": false,
          "hidden": false,
          "value": {
            "choices": "Died"
          }
        }
      ]
    }
  ]
}